sockem/__init__.py
sockem-0.1.0.dist-info/METADATA
sockem-0.1.0.dist-info/WHEEL
sockem-0.1.0.dist-info/top_level.txt
sockem-0.1.0.dist-info/RECORD
