Metadata-Version: 2.4
Name: sockem
Version: 0.1.0
Summary: A Python client for the Sockem socket server.
Requires-Python: >=3.14
Requires-Dist: websockets>=16.0
